SpeechAndLanguageProcessing2eSlp2e/README.md
SpeechAndLanguageProcessing2eSlp2e/__init__.py
SpeechAndLanguageProcessing2eSlp2e/__main__.py
SpeechAndLanguageProcessing2eSlp2e/file.pdf
SpeechAndLanguageProcessing2eSlp2e/index.html
speech_and_language_processing_2e_slp2e-2024.3.5.0.dist-info/METADATA
speech_and_language_processing_2e_slp2e-2024.3.5.0.dist-info/WHEEL
speech_and_language_processing_2e_slp2e-2024.3.5.0.dist-info/entry_points.txt
speech_and_language_processing_2e_slp2e-2024.3.5.0.dist-info/top_level.txt
speech_and_language_processing_2e_slp2e-2024.3.5.0.dist-info/RECORD
